ScienceSearcher/DataProcess.py
ScienceSearcher/DatabaseAccess.py
ScienceSearcher/DownloadClient.py
ScienceSearcher/DownloadServer.py
ScienceSearcher/ESClient.py
ScienceSearcher/PDFProcessor.py
ScienceSearcher/SearchEngine.py
ScienceSearcher/VideoProcessor.py
ScienceSearcher/__init__.py
ScienceSearcher/grobid_client/__init__.py
ScienceSearcher/grobid_client/client.py
ScienceSearcher/grobid_client/config.json
ScienceSearcher/grobid_client/grobid_client.py
ScienceSearcher-1.0.6.dist-info/LICENSE
ScienceSearcher-1.0.6.dist-info/METADATA
ScienceSearcher-1.0.6.dist-info/WHEEL
ScienceSearcher-1.0.6.dist-info/top_level.txt
ScienceSearcher-1.0.6.dist-info/RECORD
