Metadata-Version: 2.1
Name: ScienceSearcher
Version: 1.0.6
Summary: an IR system for scientific research papers
Home-page: https://github.com/BITCS-Information-Retrieval-2020/search-rattailcollagen1
Author: RatTailCollagen1
Author-email: 815398117@qq.com
License: UNKNOWN
Platform: UNKNOWN
Classifier: Programming Language :: Python :: 3
Classifier: License :: OSI Approved :: MIT License
Classifier: Operating System :: OS Independent
